langchain_mongodb/__init__.py
langchain_mongodb/cache.py
langchain_mongodb/chat_message_histories.py
langchain_mongodb/docstores.py
langchain_mongodb/index.py
langchain_mongodb/indexes.py
langchain_mongodb/loaders.py
langchain_mongodb/pipelines.py
langchain_mongodb/py.typed
langchain_mongodb/utils.py
langchain_mongodb/vectorstores.py
langchain_mongodb/agent_toolkit/__init__.py
langchain_mongodb/agent_toolkit/database.py
langchain_mongodb/agent_toolkit/prompt.py
langchain_mongodb/agent_toolkit/tool.py
langchain_mongodb/agent_toolkit/toolkit.py
langchain_mongodb/graphrag/__init__.py
langchain_mongodb/graphrag/example_templates.py
langchain_mongodb/graphrag/graph.py
langchain_mongodb/graphrag/prompts.py
langchain_mongodb/graphrag/schema.py
langchain_mongodb/retrievers/__init__.py
langchain_mongodb/retrievers/full_text_search.py
langchain_mongodb/retrievers/graphrag.py
langchain_mongodb/retrievers/hybrid_search.py
langchain_mongodb/retrievers/parent_document.py
langchain_mongodb/retrievers/self_querying.py
langchain_mongodb-0.7.1.dist-info/METADATA
langchain_mongodb-0.7.1.dist-info/WHEEL
langchain_mongodb-0.7.1.dist-info/licenses/LICENSE
langchain_mongodb-0.7.1.dist-info/RECORD
