Metadata-Version: 2.4
Name: langchain-mongodb
Version: 0.7.1
Summary: An integration package connecting MongoDB and LangChain
License-File: LICENSE
Requires-Python: >=3.9
Requires-Dist: langchain-core>=0.3
Requires-Dist: langchain-text-splitters>=0.3
Requires-Dist: langchain>=0.3
Requires-Dist: lark<2.0.0,>=1.1.9
Requires-Dist: numpy>=1.26
Requires-Dist: pymongo>=4.6.1
